connectai
