Metadata-Version: 2.1
Name: ca-lark-websocket
Version: 0.0.3
Summary: lark(feishu) client
Home-page: UNKNOWN
Author: lloydzhou@gmail.com
License: MIT
Project-URL: Documentation, https://www.connectai-e.com
Project-URL: Code, http://github.com/connectAI-E/Feishu-Webhook-Proxy
Project-URL: Issue tracker, http://github.com/connectAI-E/Feishu-Webhook-Proxy/issues
Keywords: Feishu,Lark,Webhook,Websocket,Bot
Platform: UNKNOWN
Requires-Python: >=3.8
License-File: LICENSE
